arrangebpy/__init__.py
arrangebpy/config.py
arrangebpy/layout.py
arrangebpy/settings.py
arrangebpy/utils.py
arrangebpy/arrange/__init__.py
arrangebpy/arrange/coordinates.py
arrangebpy/arrange/graph.py
arrangebpy/arrange/grid.py
arrangebpy/arrange/multi_input.py
arrangebpy/arrange/ordering.py
arrangebpy/arrange/orthogonal.py
arrangebpy/arrange/ranking.py
arrangebpy/arrange/reroute.py
arrangebpy/arrange/routing.py
arrangebpy/arrange/stacking.py
arrangebpy/arrange/structs.py
arrangebpy/arrange/sugiyama.py
arrangebpy/arrange/topological.py
arrangebpy/arrange/placement/bk.py
arrangebpy/arrange/placement/linear_segments.py
arrangebpy-0.1.0.dist-info/licenses/LICENSE
arrangebpy-0.1.0.dist-info/METADATA
arrangebpy-0.1.0.dist-info/WHEEL
arrangebpy-0.1.0.dist-info/top_level.txt
arrangebpy-0.1.0.dist-info/RECORD
