Metadata-Version: 2.4
Name: arrangebpy
Version: 0.1.0
Summary: Automatic layout of Blender node trees
Author-email: Brady Johnston <brady.johnston@me.com>
License: GPL-3.0-or-later
Project-URL: Homepage, https://bradajohnston.github.io/arrangebpy
Project-URL: Repository, https://github.com/BradyAJohnston/arrangebpy
Keywords: blender,nodes,layout,graph
Classifier: License :: OSI Approved :: GNU General Public License v3 or later (GPLv3+)
Classifier: Programming Language :: Python :: 3
Classifier: Programming Language :: Python :: 3.11
Requires-Python: ~=3.11.0
License-File: LICENSE
Requires-Dist: networkx>=3.4.2
Provides-Extra: bpy
Requires-Dist: bpy>=4.2.0; extra == "bpy"
Provides-Extra: test
Requires-Dist: pytest>=7.4.0; extra == "test"
Requires-Dist: pytest-cov>=4.1.0; extra == "test"
Requires-Dist: tox>=4.8.0; extra == "test"
Provides-Extra: docs
Requires-Dist: quartodoc; extra == "docs"
Dynamic: license-file
